[{"id":"dx_1138","Name":"cough","webmdid":"2030","isTopSymptom":"1"},{"id":"dx_4812","Name":"sore throat","webmdid":"6617","isTopSymptom":"1"},{"id":"dx_861","Name":"lump on one side of neck","webmdid":"4410","isTopSymptom":"1"},{"id":"dx_3582","Name":"choking","webmdid":"1524","isTopSymptom":"1"},{"id":"dx_3583","Name":"nasopharyngeal induration","webmdid":"4737","isTopSymptom":"0"},{"id":"dx_3584","Name":"swelling at back of throat","webmdid":"6822","isTopSymptom":"0"},{"id":"dx_3585","Name":"tumor on back of throat","webmdid":"3226","isTopSymptom":"0"},{"id":"dx_3593","Name":"cracking sound in neck","webmdid":"3196","isTopSymptom":"0"},{"id":"dx_3594","Name":"neck is blue","webmdid":"1581","isTopSymptom":"0"},{"id":"dx_3597","Name":"neck has changed colors","webmdid":"4748","isTopSymptom":"0"},{"id":"dx_3600","Name":"neck is swollen","webmdid":"4781","isTopSymptom":"1"},{"id":"dx_3601","Name":"neck is red","webmdid":"5829","isTopSymptom":"0"},{"id":"dx_3605","Name":"can't bend head forward","webmdid":"4753","isTopSymptom":"0"},{"id":"dx_3603","Name":"neck fascia thickening","webmdid":"4752","isTopSymptom":"0"},{"id":"dx_3608","Name":"infected lump or sore on neck","webmdid":"3283","isTopSymptom":"0"},{"id":"dx_3609","Name":"pea-sized lump(s) in neck","webmdid":"4756","isTopSymptom":"0"},{"id":"dx_3611","Name":"hair roots on neck are red","webmdid":"4755","isTopSymptom":"0"},{"id":"dx_3612","Name":"hair on neck feels tender","webmdid":"3287","isTopSymptom":"0"},{"id":"dx_3621","Name":"lump on neck","webmdid":"4389","isTopSymptom":"1"},{"id":"dx_3627","Name":"clearly outlined pea-sized lump on neck","webmdid":"1909","isTopSymptom":"0"},{"id":"dx_3628","Name":"prickling or tingling in neck","webmdid":"4771","isTopSymptom":"0"},{"id":"dx_3629","Name":"neck hurts","webmdid":"4759","isTopSymptom":"1"},{"id":"dx_3634","Name":"feel pressure on neck","webmdid":"4772","isTopSymptom":"0"},{"id":"dx_3636","Name":"itchy neck","webmdid":"3796","isTopSymptom":"0"},{"id":"dx_3638","Name":"short neck","webmdid":"4775","isTopSymptom":"0"},{"id":"dx_3644","Name":"stiff neck","webmdid":"4774","isTopSymptom":"1"},{"id":"dx_3645","Name":"neck subcutaneous emphysema","webmdid":"1210","isTopSymptom":"0"},{"id":"dx_3646","Name":"no fat in neck","webmdid":"4827","isTopSymptom":"0"},{"id":"dx_3647","Name":"neck does not sweat","webmdid":"4749","isTopSymptom":"0"},{"id":"dx_3649","Name":"spider vein(s) on neck","webmdid":"2250","isTopSymptom":"0"},{"id":"dx_3653","Name":"red open sore(s) on neck","webmdid":"5797","isTopSymptom":"0"},{"id":"dx_3654","Name":"neck vasodilatation","webmdid":"9281","isTopSymptom":"0"},{"id":"dx_3658","Name":"neck muscles are weak","webmdid":"4768","isTopSymptom":"0"},{"id":"dx_3650","Name":"neck tender to touch","webmdid":"4783","isTopSymptom":"1"},{"id":"dx_7323","Name":"red bumps around hair follicles on neck","webmdid":"5784","isTopSymptom":"0"},{"id":"dx_7330","Name":"pus-filled bump(s) in neck hair follicle(s)","webmdid":"5515","isTopSymptom":"0"},{"id":"dx_7395","Name":"rash limited to neck","webmdid":"5734","isTopSymptom":"1"},{"id":"dx_7633","Name":"can't turn head","webmdid":"4767","isTopSymptom":"0"},{"id":"dx_1169","Name":"cricothyroid paralysis","webmdid":"2093","isTopSymptom":"0"},{"id":"dx_1316","Name":"trouble swallowing","webmdid":"2239","isTopSymptom":"1"},{"id":"dx_1460","Name":"epiglottis swelling","webmdid":"8621","isTopSymptom":"1"},{"id":"dx_1462","Name":"epiglottic erythema","webmdid":"2446","isTopSymptom":"0"},{"id":"dx_1461","Name":"epiglottic enlargement","webmdid":"2435","isTopSymptom":"0"},{"id":"dx_1463","Name":"epiglottitis","webmdid":"2447","isTopSymptom":"0"},{"id":"dx_2065","Name":"food or liquid goes down wrong pipe","webmdid":"8186","isTopSymptom":"1"},{"id":"dx_4892","Name":"sternocleidomastoid muscle paralysis","webmdid":"5376","isTopSymptom":"0"},{"id":"dx_4918","Name":"high pitched breathing","webmdid":"4843","isTopSymptom":"1"},{"id":"dx_5123","Name":"throat burning sensation","webmdid":"7094","isTopSymptom":"1"},{"id":"dx_5125","Name":"tightness in throat","webmdid":"7140","isTopSymptom":"1"},{"id":"dx_5126","Name":"throat dryness","webmdid":"7098","isTopSymptom":"1"},{"id":"dx_5131","Name":"pain on one side of throat","webmdid":"5176","isTopSymptom":"1"},{"id":"dx_5132","Name":"tingling and prickling in throat","webmdid":"7107","isTopSymptom":"0"},{"id":"dx_5133","Name":"itchy throat","webmdid":"3806","isTopSymptom":"1"},{"id":"dx_5149","Name":"thyroid enlargement","webmdid":"2436","isTopSymptom":"1"},{"id":"dx_5148","Name":"thyroid bruit","webmdid":"7129","isTopSymptom":"0"},{"id":"dx_5151","Name":"removal of thyroid gland","webmdid":"9756","isTopSymptom":"0"},{"id":"dx_5312","Name":"head turned to one side","webmdid":"3380","isTopSymptom":"0"},{"id":"dx_5315","Name":"tracheal compression","webmdid":"7096","isTopSymptom":"0"},{"id":"dx_5316","Name":"windpipe is shifted","webmdid":"7697","isTopSymptom":"0"},{"id":"dx_5679","Name":"voice deepening","webmdid":"7547","isTopSymptom":"0"},{"id":"dx_5969","Name":"voice is hoarse","webmdid":"3505","isTopSymptom":"1"},{"id":"dx_6006","Name":"pain when I swallow","webmdid":"4959","isTopSymptom":"1"},{"id":"dx_6162","Name":"hepatojugular reflux","webmdid":"3473","isTopSymptom":"0"},{"id":"dx_2449","Name":"Hashimoto disease","webmdid":"8835","isTopSymptom":"0"},{"id":"dx_2864","Name":"jugular vein a wave increased","webmdid":"2513","isTopSymptom":"1"},{"id":"dx_2954","Name":"jugular venous distention with inspiration","webmdid":"3848","isTopSymptom":"0"},{"id":"dx_2987","Name":"laryngeal anesthesia","webmdid":"3960","isTopSymptom":"0"},{"id":"dx_2988","Name":"laryngeal crepitation","webmdid":"3195","isTopSymptom":"0"},{"id":"dx_2989","Name":"laryngeal dryness","webmdid":"3962","isTopSymptom":"0"},{"id":"dx_2990","Name":"laryngeal edema","webmdid":"3963","isTopSymptom":"0"},{"id":"dx_2991","Name":"laryngeal hematoma","webmdid":"3965","isTopSymptom":"0"},{"id":"dx_2993","Name":"laryngeal mass","webmdid":"9106","isTopSymptom":"0"},{"id":"dx_2994","Name":"laryngeal mobility increase","webmdid":"3966","isTopSymptom":"0"},{"id":"dx_2998","Name":"laryngeal obstruction","webmdid":"3967","isTopSymptom":"0"},{"id":"dx_2999","Name":"laryngeal pain","webmdid":"3968","isTopSymptom":"1"},{"id":"dx_3000","Name":"laryngeal papilloma","webmdid":"3969","isTopSymptom":"0"},{"id":"dx_3002","Name":"laryngeal pressure sensation","webmdid":"3970","isTopSymptom":"0"},{"id":"dx_3003","Name":"laryngeal erythema","webmdid":"3964","isTopSymptom":"0"},{"id":"dx_3004","Name":"laryngeal stenosis","webmdid":"3971","isTopSymptom":"0"},{"id":"dx_3005","Name":"laryngeal tenderness","webmdid":"3972","isTopSymptom":"0"},{"id":"dx_3006","Name":"laryngeal ulceration","webmdid":"9107","isTopSymptom":"0"},{"id":"dx_3008","Name":"laryngitis","webmdid":"9108","isTopSymptom":"1"},{"id":"dx_2291","Name":"globus major nodule","webmdid":"3178","isTopSymptom":"0"},{"id":"dx_2303","Name":"thyroid nodule","webmdid":"7132","isTopSymptom":"1"},{"id":"dx_795","Name":"carotid artery bruit","webmdid":"8335","isTopSymptom":"0"},{"id":"dx_796","Name":"carotid artery distention","webmdid":"8336","isTopSymptom":"0"},{"id":"dx_798","Name":"carotodynia","webmdid":"8338","isTopSymptom":"0"},{"id":"dx_802","Name":"carotid pulse increase","webmdid":"8340","isTopSymptom":"0"},{"id":"dx_799","Name":"carotid pulse absence","webmdid":"8339","isTopSymptom":"0"},{"id":"dx_797","Name":"carotid artery mass","webmdid":"8337","isTopSymptom":"0"},{"id":"dx_854","Name":"cervical lymph node bleeding","webmdid":"8378","isTopSymptom":"0"},{"id":"dx_855","Name":"neck lymph node too big","webmdid":"4763","isTopSymptom":"0"},{"id":"dx_860","Name":"tender neck lymph node","webmdid":"4762","isTopSymptom":"1"},{"id":"dx_858","Name":"painful swollen gland in front part of neck","webmdid":"8379","isTopSymptom":"1"},{"id":"dx_870","Name":"neck bones sticking out","webmdid":"7518","isTopSymptom":"1"},{"id":"dx_877","Name":"cervical stenosis","webmdid":"8391","isTopSymptom":"0"},{"id":"dx_880","Name":"cervical erosion","webmdid":"8393","isTopSymptom":"0"},{"id":"dx_881","Name":"neck bones fused together","webmdid":"3822","isTopSymptom":"1"},{"id":"dx_959","Name":"choking sensation","webmdid":"1875","isTopSymptom":"1"},{"id":"dx_8310","Name":"episodes of not breathing during sleep","webmdid":"9630","isTopSymptom":"1"},{"id":"dx_3553","Name":"food comes back up","webmdid":"2937","isTopSymptom":"1"},{"id":"dx_3655","Name":"enlarged jugular vein","webmdid":"3847","isTopSymptom":"0"},{"id":"dx_3656","Name":"neck vessel bruit","webmdid":"9282","isTopSymptom":"0"},{"id":"dx_3659","Name":"webbing on side of neck","webmdid":"6233","isTopSymptom":"0"},{"id":"dx_3922","Name":"whispered pectoriloquy","webmdid":"9364","isTopSymptom":"0"},{"id":"dx_4033","Name":"throat feels numb","webmdid":"4939","isTopSymptom":"0"},{"id":"dx_4035","Name":"throat bleeding","webmdid":"7093","isTopSymptom":"0"},{"id":"dx_4037","Name":"burn back of throat","webmdid":"1715","isTopSymptom":"0"},{"id":"dx_4039","Name":"white stuff on throat","webmdid":"5483","isTopSymptom":"1"},{"id":"dx_4044","Name":"lump on one side of throat","webmdid":"3269","isTopSymptom":"0"},{"id":"dx_4046","Name":"orange mucous in throat","webmdid":"2261","isTopSymptom":"0"},{"id":"dx_4048","Name":"pharyngeal mucous membrane edema","webmdid":"4081","isTopSymptom":"0"},{"id":"dx_4049","Name":"brown mucous in throat","webmdid":"5486","isTopSymptom":"0"},{"id":"dx_4050","Name":"white mucous in throat","webmdid":"5490","isTopSymptom":"0"},{"id":"dx_4051","Name":"throat spasm","webmdid":"7105","isTopSymptom":"0"},{"id":"dx_4052","Name":"throat feels weak","webmdid":"5492","isTopSymptom":"0"},{"id":"dx_4053","Name":"red pea-sized lump(s) in lining of throat","webmdid":"4426","isTopSymptom":"0"},{"id":"dx_4055","Name":"pharyngeal paralysis","webmdid":"5372","isTopSymptom":"0"},{"id":"dx_4056","Name":"small red or purple spots on back of throat","webmdid":"6392","isTopSymptom":"0"},{"id":"dx_4057","Name":"throat is red","webmdid":"5482","isTopSymptom":"0"},{"id":"dx_4059","Name":"throat feels tender","webmdid":"6974","isTopSymptom":"0"},{"id":"dx_4060","Name":"open sore(s) on back of throat","webmdid":"5499","isTopSymptom":"0"},{"id":"dx_4061","Name":"blister(s) on back of throat","webmdid":"1512","isTopSymptom":"0"},{"id":"dx_6741","Name":"lump on the front of neck","webmdid":"4386","isTopSymptom":"0"},{"id":"dx_6742","Name":"neck mass, anterior cervical","webmdid":"9277","isTopSymptom":"0"},{"id":"dx_6743","Name":"neck mass, posterior cervical","webmdid":"9279","isTopSymptom":"0"},{"id":"dx_7628","Name":"feels like something is stuck in my throat","webmdid":"2800","isTopSymptom":"0"},{"id":"dx_8003","Name":"throat clearing","webmdid":"7095","isTopSymptom":"1"}]